README.md
setup.py
GN/GN.py
GN/__init__.py
GN.egg-info/PKG-INFO
GN.egg-info/SOURCES.txt
GN.egg-info/dependency_links.txt
GN.egg-info/requires.txt
GN.egg-info/top_level.txt
test/test_GN.py