Metadata-Version: 2.1
Name: GN
Version: 0.1
Summary: a hierachical community detection algorithm by Girvan Newman
Home-page: https://github.com/zhaofeng-shu33/Girvan-Newman
Author: zhaofeng-shu33
Author-email: 616545598@qq.com
License: Apache License Version 2.0
Platform: UNKNOWN
Classifier: Programming Language :: Python :: 3
